README.md
pyproject.toml
src/cosyvoice/__init__.py
src/cosyvoice/bin/average_model.py
src/cosyvoice/bin/export_jit.py
src/cosyvoice/bin/export_onnx.py
src/cosyvoice/bin/inference_deprecated.py
src/cosyvoice/bin/train.py
src/cosyvoice/cli/__init__.py
src/cosyvoice/cli/cosyvoice.py
src/cosyvoice/cli/frontend.py
src/cosyvoice/cli/model.py
src/cosyvoice/dataset/__init__.py
src/cosyvoice/dataset/dataset.py
src/cosyvoice/dataset/processor.py
src/cosyvoice/flow/decoder.py
src/cosyvoice/flow/flow.py
src/cosyvoice/flow/flow_matching.py
src/cosyvoice/flow/length_regulator.py
src/cosyvoice/hifigan/discriminator.py
src/cosyvoice/hifigan/f0_predictor.py
src/cosyvoice/hifigan/generator.py
src/cosyvoice/hifigan/hifigan.py
src/cosyvoice/llm/llm.py
src/cosyvoice/tokenizer/tokenizer.py
src/cosyvoice/tokenizer/assets/multilingual_zh_ja_yue_char_del.tiktoken
src/cosyvoice/transformer/__init__.py
src/cosyvoice/transformer/activation.py
src/cosyvoice/transformer/attention.py
src/cosyvoice/transformer/convolution.py
src/cosyvoice/transformer/decoder.py
src/cosyvoice/transformer/decoder_layer.py
src/cosyvoice/transformer/embedding.py
src/cosyvoice/transformer/encoder.py
src/cosyvoice/transformer/encoder_layer.py
src/cosyvoice/transformer/label_smoothing_loss.py
src/cosyvoice/transformer/positionwise_feed_forward.py
src/cosyvoice/transformer/subsampling.py
src/cosyvoice/transformer/upsample_encoder.py
src/cosyvoice/utils/__init__.py
src/cosyvoice/utils/class_utils.py
src/cosyvoice/utils/common.py
src/cosyvoice/utils/executor.py
src/cosyvoice/utils/file_utils.py
src/cosyvoice/utils/frontend_utils.py
src/cosyvoice/utils/losses.py
src/cosyvoice/utils/mask.py
src/cosyvoice/utils/scheduler.py
src/cosyvoice/utils/train_utils.py
src/cosyvoice/vllm/cosyvoice2.py
src/matcha/__init__.py
src/matcha/app.py
src/matcha/cli.py
src/matcha/train.py
src/matcha/hifigan/__init__.py
src/matcha/hifigan/config.py
src/matcha/hifigan/denoiser.py
src/matcha/hifigan/env.py
src/matcha/hifigan/meldataset.py
src/minicpmo.egg-info/PKG-INFO
src/minicpmo.egg-info/SOURCES.txt
src/minicpmo.egg-info/dependency_links.txt
src/minicpmo.egg-info/requires.txt
src/minicpmo.egg-info/top_level.txt
