Metadata-Version: 2.4
Name: minicpmo
Version: 0.1.2
Summary: Unified utilities package for MiniCPM-o: includes cosyvoice + stepaudio2 and extensible utils.
Author: MiniCPM-o Utils Maintainers
License: Apache-2.0
Keywords: minicpmo,audio,tts,utils,cosyvoice,stepaudio2
Classifier: Development Status :: 4 - Beta
Classifier: Intended Audience :: Developers
Classifier: License :: OSI Approved :: Apache Software License
Classifier: Programming Language :: Python :: 3
Classifier: Programming Language :: Python :: 3.10
Classifier: Programming Language :: Python :: 3.11
Classifier: Programming Language :: Python :: 3.12
Requires-Python: >=3.10
Requires-Dist: numpy
Requires-Dist: pillow
Requires-Dist: librosa
Requires-Dist: decord
Requires-Dist: moviepy
Provides-Extra: tts
Requires-Dist: torch>=2.3.0; extra == "tts"
Requires-Dist: torchaudio>=2.3.0; extra == "tts"
Requires-Dist: transformers>=4.49.0; extra == "tts"
Requires-Dist: hyperpyyaml; extra == "tts"
Requires-Dist: openai-whisper; extra == "tts"
Requires-Dist: tqdm; extra == "tts"
Requires-Dist: tiktoken; extra == "tts"
Requires-Dist: inflect; extra == "tts"
Requires-Dist: omegaconf; extra == "tts"
Requires-Dist: einops; extra == "tts"
Provides-Extra: streaming
Requires-Dist: minicpmo-utils[tts]; extra == "streaming"
Requires-Dist: onnxruntime>=1.18.0; extra == "streaming"
Requires-Dist: onnx; extra == "streaming"
Requires-Dist: diffusers; extra == "streaming"
Provides-Extra: gpu
Requires-Dist: onnxruntime-gpu>=1.18.0; sys_platform == "linux" and extra == "gpu"
Provides-Extra: all
Requires-Dist: minicpmo-utils[gpu,streaming,tts]; extra == "all"
